nfsefoz/__init__.py
nfsefoz/client.py
nfsefoz/utils.py
nfsefoz/xml.py
nfsefoz-0.0.4.dist-info/licenses/LICENSE
nfsefoz-0.0.4.dist-info/METADATA
nfsefoz-0.0.4.dist-info/WHEEL
nfsefoz-0.0.4.dist-info/top_level.txt
nfsefoz-0.0.4.dist-info/RECORD
